nonebot_plugin_error_show/__init__.py
nonebot_plugin_error_show/__main__.py
nonebot_plugin_error_show/config.py
nonebot_plugin_error_show/db.py
nonebot_plugin_error_show/handle.py
nonebot_plugin_error_show/migrations/f93a91fba37c_init_error_show_db.py
nonebot_plugin_error_show/templates/error.html.jinja2
nonebot_plugin_error_show/templates/input.css
nonebot_plugin_error_show/templates/output.css
nonebot_plugin_error_show/utils.py
nonebot_plugin_error_show-0.1.2.dist-info/WHEEL
nonebot_plugin_error_show-0.1.2.dist-info/METADATA
nonebot_plugin_error_show-0.1.2.dist-info/RECORD
