Metadata-Version: 2.3
Name: nonebot-plugin-error-show
Version: 0.1.2
Summary: nonebot的报错提示插件
Author: zifox666
Author-email: zifox666 <zifox666@gmail.com>
Requires-Dist: nonebot2>=2.4.2,<3.0.0
Requires-Dist: nonebot-plugin-localstore>=0.7.4,<1.0.0
Requires-Dist: nonebot-plugin-alconna>=0.59.3,<1.0.0
Requires-Dist: nonebot-plugin-htmlrender>=0.6.6
Requires-Dist: qrcode[pil]>=8.2
Requires-Dist: nonebot-plugin-orm[default]>=0.8.2
Requires-Dist: nonebot-plugin-uninfo>=0.9.0
Requires-Python: >=3.10
Project-URL: Repository, https://github.com/zifox666/nonebot-plugin-error-show
